datasette_json_preview/__init__.py
datasette_json_preview-0.3.dist-info/METADATA
datasette_json_preview-0.3.dist-info/WHEEL
datasette_json_preview-0.3.dist-info/entry_points.txt
datasette_json_preview-0.3.dist-info/top_level.txt
datasette_json_preview-0.3.dist-info/RECORD
