Metadata-Version: 2.1
Name: datasette-json-preview
Version: 0.3
Summary: Preview of new JSON default format for Datasette, see issue #782
Home-page: https://github.com/simonw/datasette-json-preview
Author: Simon Willison
License: Apache License, Version 2.0
Project-URL: Issues, https://github.com/simonw/datasette-json-preview/issues
Project-URL: CI, https://github.com/simonw/datasette-json-preview/actions
Project-URL: Changelog, https://github.com/simonw/datasette-json-preview/releases
Platform: UNKNOWN
Requires-Dist: datasette (>=0.55)
Provides-Extra: test
Requires-Dist: pytest ; extra == 'test'
Requires-Dist: pytest-asyncio ; extra == 'test'
Requires-Dist: httpx ; extra == 'test'
Requires-Dist: sqlite-utils ; extra == 'test'
